zkb/__init__.py
zkb/cli.py
zkb/db.py
zkb/note.py
zkb/zkb.py
zkb-0.1.1.dist-info/METADATA
zkb-0.1.1.dist-info/WHEEL
zkb-0.1.1.dist-info/licenses/LICENSE
zkb-0.1.1.dist-info/RECORD
