Metadata-Version: 2.3
Name: zkb
Version: 0.1.1
Summary: A Zettelkasten-inspired knowledge base
Project-URL: GitHub, https://github.com/witt3rd/zkb
Author-email: Donald Thompson <witt3rd@witt3rd.com>
License-File: LICENSE
Requires-Python: >=3.8
Requires-Dist: loguru>=0.7.2
Requires-Dist: python-dotenv>=1.0.1
Requires-Dist: pyyaml>=6.0.1
Requires-Dist: qa-store>=0.2.1
